CHANGES.txt
LICENSE
MANIFEST.in
README.txt
setup.py
factuursturen/__init__.py
factuursturen.egg-info/PKG-INFO
factuursturen.egg-info/SOURCES.txt
factuursturen.egg-info/dependency_links.txt
factuursturen.egg-info/requires.txt
factuursturen.egg-info/top_level.txt
factuursturen/test/test_client.py