Metadata-Version: 1.0
Name: factuursturen
Version: 0.4
Summary: a REST client class for the API of www.factuursturen.nl
Home-page: https://github.com/reinoud/factuursturen
Author: Reinoud van Leeuwen
Author-email: reinoud.v@n.leeuwen.net
License: Copyright (c) 2013, Reinoud van Leeuwen
